pycondor/__init__.py
pycondor/__version__.py
pycondor/basenode.py
pycondor/cli.py
pycondor/compatibility.py
pycondor/dagman.py
pycondor/job.py
pycondor/utils.py
pycondor/visualize.py
pycondor/tests/__init__.py
pycondor/tests/example_script.py
pycondor/tests/test_basenode.py
pycondor/tests/test_cli.py
pycondor/tests/test_dagman.py
pycondor/tests/test_job.py
pycondor/tests/test_utils.py
pycondor/tests/test_visualize.py
PyCondor-0.6.0.dist-info/LICENSE
PyCondor-0.6.0.dist-info/METADATA
PyCondor-0.6.0.dist-info/WHEEL
PyCondor-0.6.0.dist-info/entry_points.txt
PyCondor-0.6.0.dist-info/top_level.txt
PyCondor-0.6.0.dist-info/RECORD
